gutenberg2kindle/__init__.py
gutenberg2kindle/cli.py
gutenberg2kindle/config.py
gutenberg2kindle/email.py
gutenberg2kindle/gutenberg.py
gutenberg2kindle-0.7.0.dist-info/LICENSE
gutenberg2kindle-0.7.0.dist-info/METADATA
gutenberg2kindle-0.7.0.dist-info/WHEEL
gutenberg2kindle-0.7.0.dist-info/entry_points.txt
gutenberg2kindle-0.7.0.dist-info/RECORD
