Metadata-Version: 2.1
Name: gutenberg2kindle
Version: 0.7.0
Summary: A small Python tool to download and send ebooks from Project Gutenberg to a Kindle email address via SMTP
Home-page: https://github.com/aitorres/gutenberg2kindle
License: AGPL-3.0-only
Keywords: python,cli,ebooks,kindle,gutenberg,project gutenberg
Author: Andrés Ignacio Torres
Author-email: dev@aitorres.com
Requires-Python: >=3.9,<4.0
Classifier: Development Status :: 3 - Alpha
Classifier: Environment :: Console
Classifier: Intended Audience :: Developers
Classifier: Intended Audience :: Education
Classifier: Intended Audience :: Science/Research
Classifier: License :: OSI Approved :: GNU Affero General Public License v3
Classifier: Operating System :: OS Independent
Classifier: Programming Language :: Python :: 3
Classifier: Programming Language :: Python :: 3.9
Classifier: Programming Language :: Python :: 3.10
Classifier: Programming Language :: Python :: 3.11
Classifier: Topic :: Communications :: File Sharing
Classifier: Topic :: Utilities
Classifier: Typing :: Typed
Requires-Dist: requests (>=2.31.0,<3.0.0)
Requires-Dist: usersettings (>=1.1.5,<2.0.0)
Project-URL: Bug Tracker, https://github.com/aitorres/gutenberg2kindle/issues
Project-URL: Change Log, https://github.com/aitorres/gutenberg2kindle/blob/main/CHANGELOG.md
Project-URL: Repository, https://github.com/aitorres/gutenberg2kindle
